spider/__init__.py
spider/browser.py
spider/deep_spider.py
spider/media_spider.py
spider/page_spider.py
spider/scorll_spider.py
spider_ms-1.0.2.dist-info/LICENSE
spider_ms-1.0.2.dist-info/METADATA
spider_ms-1.0.2.dist-info/WHEEL
spider_ms-1.0.2.dist-info/top_level.txt
spider_ms-1.0.2.dist-info/RECORD
