Metadata-Version: 2.1
Name: spider_ms
Version: 1.0.2
Summary: 一个高级爬虫框架
Home-page: https://github.com/musen123
Author: MuSen
Author-email: 121292678@qq.com
Classifier: Programming Language :: Python :: 3
Requires-Python: >=3.8
License-File: LICENSE
Requires-Dist: moviepy ==1.0.3
Requires-Dist: pillow ==10.3.0
Requires-Dist: playwright ==1.44.0
Requires-Dist: faker ==25.8.0
Requires-Dist: requests ==2.32.3
